num_thai_cnv/__init__.py
num_thai_cnv/num_thai_cnv.py
num_thai_cnv-1.0.1.dist-info/License.txt
num_thai_cnv-1.0.1.dist-info/METADATA
num_thai_cnv-1.0.1.dist-info/WHEEL
num_thai_cnv-1.0.1.dist-info/top_level.txt
num_thai_cnv-1.0.1.dist-info/RECORD
