Metadata-Version: 2.1
Name: num-thai-cnv
Version: 1.0.1
Summary: Thai localization package
Home-page: UNKNOWN
Author: Natthakhon Laosurasuntorn
Author-email: nattlao@gmail.com
License: UNKNOWN
Keywords: num,thai
Platform: UNKNOWN
Classifier: Programming Language :: Python :: 3
Classifier: License :: OSI Approved :: MIT License
Classifier: Operating System :: OS Independent
Requires-Python: >=3.6
